MANIFEST.in
README
requirements.txt
setup.cfg
setup.py
vital/__init__.py
vital/cache/__init__.py
vital/cache/async_decorators.py
vital/cache/decorators.py
vital/debug/__init__.py
vital/debug/colors.py
vital/debug/stats.py
vital/debug/tlds.py
vital/security/__init__.py
vital/tools/__init__.py
vital/tools/dicts.py
vital/tools/encoding.py
vital/tools/html.py
vital/tools/http.py
vital/tools/lists.py
vital/tools/strings.py
vital/tools/systools.py
vital_tools.egg-info/PKG-INFO
vital_tools.egg-info/SOURCES.txt
vital_tools.egg-info/dependency_links.txt
vital_tools.egg-info/requires.txt
vital_tools.egg-info/top_level.txt