Metadata-Version: 1.0
Name: vital-tools
Version: 0.1.9
Summary: Vital tools for writing Python 3.4+ packages.
Home-page: https://github.com/jaredlunde/vital-tools
Author: Jared Lunde
Author-email: jared.lunde@gmail.com
License: MIT
Platform: UNKNOWN
